LICENSE
MANIFEST.in
README.md
requirements.txt
setup.py
cve_ape/__init__.py
cve_ape/async_utils.py
cve_ape/cli.py
cve_ape/cve_scanner.py
cve_ape/cvedb.py
cve_ape/egg_updater.py
cve_ape/error_handler.py
cve_ape/linkify.py
cve_ape/log.py
cve_ape/nvd_api.py
cve_ape/package_processor.py
cve_ape/theme.py
cve_ape/util.py
cve_ape/version.py
cve_ape.egg-info/PKG-INFO
cve_ape.egg-info/SOURCES.txt
cve_ape.egg-info/dependency_links.txt
cve_ape.egg-info/entry_points.txt
cve_ape.egg-info/requires.txt
cve_ape.egg-info/top_level.txt
cve_ape/output_engine/__init__.py
cve_ape/output_engine/console.py
cve_ape/output_engine/util.py