Metadata-Version: 2.1
Name: cve-ape
Version: 1.1.0
Summary: CVE scanner which can process pkglists
Home-page: https://github.com/Baalmor/cve-ape
Author: Alexey Perepechko
Author-email: alexey.perepechko@gmail.com
Maintainer: Alexey Perepechko
Maintainer-email: alexey.perepechko@gmail.com
License: MIT
Project-URL: Bug Reports, https://github.com/Baalmor/cve-ape/issues
Project-URL: Source, https://github.com/Baalmor/cve-ape
Keywords: security,tools,CVE
Platform: UNKNOWN
Classifier: Development Status :: 5 - Production/Stable
Classifier: Intended Audience :: Developers
Classifier: License :: OSI Approved :: MIT License
Classifier: Natural Language :: English
Classifier: Operating System :: OS Independent
Classifier: Programming Language :: Python :: 3.7
Classifier: Programming Language :: Python :: 3.8
Classifier: Programming Language :: Python :: 3.9
Classifier: Programming Language :: Python :: 3.10
Classifier: Programming Language :: Python :: Implementation :: CPython
Classifier: Programming Language :: Python :: Implementation :: PyPy
License-File: LICENSE
